Workbook
Name Slicer_Gender: #N/A
Name Slicer_Legal_Action_Taken: #N/A
Name Slicer_Loan_Type: #N/A
Name Slicer_Recovery_Status: #N/A

Sheet Pivot Tables
A3: Count of Loan_ID | H3: Row Labels | I3: Sum of Loan_Amount | K3: Row Labels | L3: Sum of Loan_Amount | O3: Row Labels | P3: Count of Loan_ID | R3: Row Labels | S3: Count of Borrower_ID | U3: Sum of Outstanding_Loan_Amount | X3: Average of Loan_Tenure
A4: 500 | H4: Business Owner | I4: 0.10461233 | K4: BRW_435 | L4: 1977716 | O4: Female | P4: 189 | R4: 21-30 | S4: 0.218 | U4: 2.8136299e+08 | X4: 46.104
H5: Self-Employed | I5: 0.3122961 | K5: BRW_13 | L5: 1980750 | O5: Male | P5: 311 | R5: 31-40 | S5: 0.186
A6: Sum of Outstanding_Loan_Amount | B6: Column Labels | H6: Salaried | I6: 0.58309157 | K6: BRW_225 | L6: 1989253 | R6: 41-50 | S6: 0.258
A7: Row Labels | B7: Fully Recovered | C7: Partially Recovered | D7: Written Off | K7: BRW_250 | L7: 1995049 | R7: 51-60 | S7: 0.254
A8: Auto | B8: 31622940 | C8: 13243439 | D8: 2894331.5 | K8: BRW_420 | L8: 1995325 | O8: Row Labels | P8: Count of Loan_ID | R8: 61-70 | S8: 0.084 | U8: Sum of Loan_Amount
A9: Business | B9: 18361305 | C9: 7289312.8 | D9: 4082090.7 | O9: Business | P9: 0.098 | U9: 512453516
A10: Home | B10: 58138125 | C10: 20567808 | D10: 3304848.4 | O10: Auto | P10: 0.174
A11: Personal | B11: 65336943 | C11: 44018534 | D11: 12503311 | F11: Row Labels | G11: Sum of Loan_Amount | O11: Home | P11: 0.288
F12: Fully Recovered | G12: 308463272 | O12: Personal | P12: 0.44
F13: Partially Recovered | G13: 160920640 | S13: Loan_Tenure | T13: Sum of Loan_Amount | U13: Sum of Outstanding_Loan_Amount
F14: Written Off | G14: 43069604 | S14: 12 | T14: 45397385 | U14: 24658775
S15: 24 | T15: 56466359 | U15: 33748662
S16: 36 | T16: 112137378 | U16: 59711460
S17: 48 | T17: 104924774 | U17: 55143429
I18: Average of Loan_Tenure | S18: 60 | T18: 106701823 | U18: 57889661
I19: 46.104 | S19: 72 | T19: 86825797 | U19: 50211000
I22: Sum of Outstanding_Loan_Amount
I23: 2.8136299e+08
I27: Sum of Loan_Amount
I28: 512453516
I31: Row Labels | J31: Sum of Loan_Amount
I32: Calls | J32: 130497629
I33: Debt Collectors | J33: 130149708
I34: Legal Notice | J34: 136185135
I35: Settlement Offer | J35: 115621044

Sheet Dashboard

Sheet New Table
A1: Borrower_ID | B1: Age | C1: Gender | D1: Employment_Type | E1: Monthly_Income | F1: Num_Dependents | G1: Loan_ID | H1: Loan_Amount | I1: Loan_Tenure | J1: Interest_Rate | K1: Loan_Type | L1: Collateral_Value | M1: Outstanding_Loan_Amount | N1: Monthly_EMI | O1: Payment_History | P1: Num_Missed_Payments | Q1: Days_Past_Due | R1: Recovery_Status | S1: Collection_Attempts | T1: Collection_Method | U1: Legal_Action_Taken
A2: BRW_1 | B2: 59 | C2: Male | D2: Salaried | E2: 215422 | F2: 0 | G2: LN_1 | H2: 1445796 | I2: 60 | J2: 12.39 | K2: Home | L2: 1727997.3 | M2: 291413.01 | N2: 4856.88 | O2: On-Time | P2: 0 | Q2: 0 | R2: Partially Recovered | S2: 1 | T2: Settlement Offer | U2: No
A3: BRW_2 | B3: 49 | C3: Female | D3: Salaried | E3: 60893 | F3: 0 | G3: LN_2 | H3: 1044620 | I3: 12 | J3: 13.47 | K3: Auto | L3: 1180032.4 | M3: 665204.15 | N3: 55433.68 | O3: On-Time | P3: 0 | Q3: 0 | R3: Fully Recovered | S3: 2 | T3: Settlement Offer | U3: No
A4: BRW_3 | B4: 35 | C4: Male | D4: Salaried | E4: 116520 | F4: 1 | G4: LN_3 | H4: 1923410 | I4: 72 | J4: 7.74 | K4: Home | L4: 2622539.9 | M4: 1031372 | N4: 14324.61 | O4: Delayed | P4: 2 | Q4: 124 | R4: Fully Recovered | S4: 2 | T4: Legal Notice | U4: No
A5: BRW_4 | B5: 63 | C5: Female | D5: Salaried | E5: 140818 | F5: 2 | G5: LN_4 | H5: 1811663 | I5: 36 | J5: 12.23 | K5: Home | L5: 1145492.7 | M5: 224973.92 | N5: 6249.28 | O5: On-Time | P5: 1 | Q5: 56 | R5: Fully Recovered | S5: 2 | T5: Calls | U5: No
A6: BRW_5 | B6: 28 | C6: Male | D6: Salaried | E6: 76272 | F6: 1 | G6: LN_5 | H6: 88578 | I6: 48 | J6: 16.13 | K6: Personal | L6: 0 | M6: 39189.892 | N6: 816.46 | O6: On-Time | P6: 1 | Q6: 69 | R6: Fully Recovered | S6: 0 | T6: Debt Collectors | U6: No
A7: BRW_6 | B7: 41 | C7: Male | D7: Salaried | E7: 238224 | F7: 3 | G7: LN_6 | H7: 664741 | I7: 36 | J7: 15.86 | K7: Auto | L7: 982214.63 | M7: 129965.53 | N7: 3610.15 | O7: On-Time | P7: 1 | Q7: 111 | R7: Partially Recovered | S7: 6 | T7: Legal Notice | U7: No
A8: BRW_7 | B8: 59 | C8: Female | D8: Self-Employed | E8: 82649 | F8: 1 | G8: LN_7 | H8: 1514110 | I8: 60 | J8: 17.06 | K8: Home | L8: 1639218.9 | M8: 875490.42 | N8: 14591.51 | O8: On-Time | P8: 0 | Q8: 0 | R8: Partially Recovered | S8: 8 | T8: Debt Collectors | U8: No
A9: BRW_8 | B9: 39 | C9: Male | D9: Salaried | E9: 79674 | F9: 0 | G9: LN_8 | H9: 912147 | I9: 12 | J9: 9.76 | K9: Personal | L9: 0 | M9: 416121.38 | N9: 34676.78 | O9: Delayed | P9: 0 | Q9: 0 | R9: Fully Recovered | S9: 0 | T9: Settlement Offer | U9: No
A10: BRW_9 | B10: 43 | C10: Male | D10: Self-Employed | E10: 159832 | F10: 3 | G10: LN_9 | H10: 258859 | I10: 72 | J10: 9.13 | K10: Home | L10: 387116.94 | M10: 168733.8 | N10: 2343.53 | O10: On-Time | P10: 3 | Q10: 124 | R10: Fully Recovered | S10: 3 | T10: Settlement Offer | U10: No
A11: BRW_10 | B11: 31 | C11: Male | D11: Self-Employed | E11: 167999 | F11: 0 | G11: LN_10 | H11: 161435 | I11: 60 | J11: 14.74 | K11: Personal | L11: 0 | M11: 133190.65 | N11: 2219.84 | O11: Delayed | P11: 0 | Q11: 0 | R11: Partially Recovered | S11: 6 | T11: Legal Notice | U11: No
A12: BRW_11 | B12: 31 | C12: Male | D12: Business Owner | E12: 101475 | F12: 2 | G12: LN_11 | H12: 790389 | I12: 24 | J12: 10.6 | K12: Auto | L12: 1115645.7 | M12: 292208.25 | N12: 12175.34 | O12: On-Time | P12: 0 | Q12: 0 | R12: Fully Recovered | S12: 0 | T12: Calls | U12: No
A13: BRW_12 | B13: 44 | C13: Female | D13: Self-Employed | E13: 76367 | F13: 0 | G13: LN_12 | H13: 1250114 | I13: 60 | J13: 6.14 | K13: Home | L13: 901978.84 | M13: 1207475 | N13: 20124.58 | O13: On-Time | P13: 0 | Q13: 0 | R13: Fully Recovered | S13: 1 | T13: Settlement Offer | U13: No
... A501: BRW_500 | B501: 61 | C501: Male | D501: Self-Employed | E501: 40169 | F501: 1 | G501: LN_500 | H501: 394866 | I501: 12 | J501: 9.14 | K501: Personal | L501: 0 | M501: 188158.08 | N501: 15679.84 | O501: On-Time | P501: 1 | Q501: 116 | R501: Written Off | S501: 6 | T501: Settlement Offer | U501: Yes

Sheet loan-recovery
A1: Borrower_ID | B1: Age | C1: Gender | D1: Employment_Type | E1: Monthly_Income | F1: Num_Dependents | G1: Loan_ID | H1: Loan_Amount | I1: Loan_Tenure | J1: Interest_Rate | K1: Loan_Type | L1: Collateral_Value | M1: Outstanding_Loan_Amount | N1: Monthly_EMI | O1: Payment_History | P1: Num_Missed_Payments | Q1: Days_Past_Due | R1: Recovery_Status | S1: Collection_Attempts | T1: Collection_Method | U1: Legal_Action_Taken
A2: BRW_1 | B2: 59 | C2: Male | D2: Salaried | E2: 215422 | F2: 0 | G2: LN_1 | H2: 1445796 | I2: 60 | J2: 12.39 | K2: Home | L2: 1727997.3 | M2: 291413.01 | N2: 4856.88 | O2: On-Time | P2: 0 | Q2: 0 | R2: Partially Recovered | S2: 1 | T2: Settlement Offer | U2: No
A3: BRW_2 | B3: 49 | C3: Female | D3: Salaried | E3: 60893 | F3: 0 | G3: LN_2 | H3: 1044620 | I3: 12 | J3: 13.47 | K3: Auto | L3: 1180032.4 | M3: 665204.15 | N3: 55433.68 | O3: On-Time | P3: 0 | Q3: 0 | R3: Fully Recovered | S3: 2 | T3: Settlement Offer | U3: No
A4: BRW_3 | B4: 35 | C4: Male | D4: Salaried | E4: 116520 | F4: 1 | G4: LN_3 | H4: 1923410 | I4: 72 | J4: 7.74 | K4: Home | L4: 2622539.9 | M4: 1031372 | N4: 14324.61 | O4: Delayed | P4: 2 | Q4: 124 | R4: Fully Recovered | S4: 2 | T4: Legal Notice | U4: No
A5: BRW_4 | B5: 63 | C5: Female | D5: Salaried | E5: 140818 | F5: 2 | G5: LN_4 | H5: 1811663 | I5: 36 | J5: 12.23 | K5: Home | L5: 1145492.7 | M5: 224973.92 | N5: 6249.28 | O5: On-Time | P5: 1 | Q5: 56 | R5: Fully Recovered | S5: 2 | T5: Calls | U5: No
A6: BRW_5 | B6: 28 | C6: Male | D6: Salaried | E6: 76272 | F6: 1 | G6: LN_5 | H6: 88578 | I6: 48 | J6: 16.13 | K6: Personal | L6: 0 | M6: 39189.892 | N6: 816.46 | O6: On-Time | P6: 1 | Q6: 69 | R6: Fully Recovered | S6: 0 | T6: Debt Collectors | U6: No
A7: BRW_6 | B7: 41 | C7: Male | D7: Salaried | E7: 238224 | F7: 3 | G7: LN_6 | H7: 664741 | I7: 36 | J7: 15.86 | K7: Auto | L7: 982214.63 | M7: 129965.53 | N7: 3610.15 | O7: On-Time | P7: 1 | Q7: 111 | R7: Partially Recovered | S7: 6 | T7: Legal Notice | U7: No
A8: BRW_7 | B8: 59 | C8: Female | D8: Self-Employed | E8: 82649 | F8: 1 | G8: LN_7 | H8: 1514110 | I8: 60 | J8: 17.06 | K8: Home | L8: 1639218.9 | M8: 875490.42 | N8: 14591.51 | O8: On-Time | P8: 0 | Q8: 0 | R8: Partially Recovered | S8: 8 | T8: Debt Collectors | U8: No
A9: BRW_8 | B9: 39 | C9: Male | D9: Salaried | E9: 79674 | F9: 0 | G9: LN_8 | H9: 912147 | I9: 12 | J9: 9.76 | K9: Personal | L9: 0 | M9: 416121.38 | N9: 34676.78 | O9: Delayed | P9: 0 | Q9: 0 | R9: Fully Recovered | S9: 0 | T9: Settlement Offer | U9: No
A10: BRW_9 | B10: 43 | C10: Male | D10: Self-Employed | E10: 159832 | F10: 3 | G10: LN_9 | H10: 258859 | I10: 72 | J10: 9.13 | K10: Home | L10: 387116.94 | M10: 168733.8 | N10: 2343.53 | O10: On-Time | P10: 3 | Q10: 124 | R10: Fully Recovered | S10: 3 | T10: Settlement Offer | U10: No
A11: BRW_10 | B11: 31 | C11: Male | D11: Self-Employed | E11: 167999 | F11: 0 | G11: LN_10 | H11: 161435 | I11: 60 | J11: 14.74 | K11: Personal | L11: 0 | M11: 133190.65 | N11: 2219.84 | O11: Delayed | P11: 0 | Q11: 0 | R11: Partially Recovered | S11: 6 | T11: Legal Notice | U11: No
A12: BRW_11 | B12: 31 | C12: Male | D12: Business Owner | E12: 101475 | F12: 2 | G12: LN_11 | H12: 790389 | I12: 24 | J12: 10.6 | K12: Auto | L12: 1115645.7 | M12: 292208.25 | N12: 12175.34 | O12: On-Time | P12: 0 | Q12: 0 | R12: Fully Recovered | S12: 0 | T12: Calls | U12: No
A13: BRW_12 | B13: 44 | C13: Female | D13: Self-Employed | E13: 76367 | F13: 0 | G13: LN_12 | H13: 1250114 | I13: 60 | J13: 6.14 | K13: Home | L13: 901978.84 | M13: 1207475 | N13: 20124.58 | O13: On-Time | P13: 0 | Q13: 0 | R13: Fully Recovered | S13: 1 | T13: Settlement Offer | U13: No
... A501: BRW_500 | B501: 61 | C501: Male | D501: Self-Employed | E501: 40169 | F501: 1 | G501: LN_500 | H501: 394866 | I501: 12 | J501: 9.14 | K501: Personal | L501: 0 | M501: 188158.08 | N501: 15679.84 | O501: On-Time | P501: 1 | Q501: 116 | R501: Written Off | S501: 6 | T501: Settlement Offer | U501: Yes

Sheet Kutools_Chart
B1: Others | C1: Missed Payments
A2: =IF('Pivot Tables'!A16<>"",'Pivot Tables'!A16,"") | B2: =IF('Pivot Tables'!B16="",NA(),'Pivot Tables'!B16) -> #N/A | C2: =IF(AND(3<='Pivot Tables'!B16,'Pivot Tables'!B16<=11),'Pivot Tables'!B16,NA()) -> #N/A
A3: =IF('Pivot Tables'!A17<>"",'Pivot Tables'!A17,"") | B3: =IF('Pivot Tables'!B17="",NA(),'Pivot Tables'!B17) -> #N/A | C3: =IF(AND(3<='Pivot Tables'!B17,'Pivot Tables'!B17<=11),'Pivot Tables'!B17,NA()) -> #N/A
A4: =IF('Pivot Tables'!A18<>"",'Pivot Tables'!A18,"") | B4: =IF('Pivot Tables'!B18="",NA(),'Pivot Tables'!B18) -> #N/A | C4: =IF(AND(3<='Pivot Tables'!B18,'Pivot Tables'!B18<=11),'Pivot Tables'!B18,NA()) -> #N/A
A5: =IF('Pivot Tables'!A19<>"",'Pivot Tables'!A19,"") | B5: =IF('Pivot Tables'!B19="",NA(),'Pivot Tables'!B19) -> #N/A | C5: =IF(AND(3<='Pivot Tables'!B19,'Pivot Tables'!B19<=11),'Pivot Tables'!B19,NA()) -> #N/A
A6: =IF('Pivot Tables'!A20<>"",'Pivot Tables'!A20,"") | B6: =IF('Pivot Tables'!B20="",NA(),'Pivot Tables'!B20) -> #N/A | C6: =IF(AND(3<='Pivot Tables'!B20,'Pivot Tables'!B20<=11),'Pivot Tables'!B20,NA()) -> #N/A
A7: =IF('Pivot Tables'!A21<>"",'Pivot Tables'!A21,"") | B7: =IF('Pivot Tables'!B21="",NA(),'Pivot Tables'!B21) -> #N/A | C7: =IF(AND(3<='Pivot Tables'!B21,'Pivot Tables'!B21<=11),'Pivot Tables'!B21,NA()) -> #N/A
A8: =IF('Pivot Tables'!A22<>"",'Pivot Tables'!A22,"") | B8: =IF('Pivot Tables'!B22="",NA(),'Pivot Tables'!B22) -> #N/A | C8: =IF(AND(3<='Pivot Tables'!B22,'Pivot Tables'!B22<=11),'Pivot Tables'!B22,NA()) -> #N/A
A9: =IF('Pivot Tables'!A23<>"",'Pivot Tables'!A23,"") | B9: =IF('Pivot Tables'!B23="",NA(),'Pivot Tables'!B23) -> #N/A | C9: =IF(AND(3<='Pivot Tables'!B23,'Pivot Tables'!B23<=11),'Pivot Tables'!B23,NA()) -> #N/A
A10: =IF('Pivot Tables'!A24<>"",'Pivot Tables'!A24,"") | B10: =IF('Pivot Tables'!B24="",NA(),'Pivot Tables'!B24) -> #N/A | C10: =IF(AND(3<='Pivot Tables'!B24,'Pivot Tables'!B24<=11),'Pivot Tables'!B24,NA()) -> #N/A
A11: Note: This data table is added when creating the chart. Errors may occur to the Color Grouping Chart if you modify or remove the data table.
